amisui-0.1.6.dist-info/METADATA
amisui-0.1.6.dist-info/WHEEL
amisui-0.1.6.dist-info/licenses/LICENSE
amisui/__init__.py
amisui/components.py
amisui/config.py
amisui/constants.py
amisui/templates/app.jinja2
amisui/templates/page.jinja2
amisui/types.py
amisui-0.1.6.dist-info/RECORD
