Metadata-Version: 2.1
Name: amisui
Version: 0.1.6
Summary: Default template for PDM package
Author-Email: luxuncang <luxuncang@qq.com>
License: Apache-2.0
Requires-Python: >3.7
Requires-Dist: pydantic>=1.10.14
Requires-Dist: jinja2>=3.1.3
